{
  "name": "essential-oils-bot",
  "version": "1.0.0",
  "description": "Telegram bot for essential oils recommendations with n8n",
  "main": "index.js",
  "scripts": {
    "start": "n8n start",
    "dev": "n8n start --tunnel",
    "test": "node test_supabase_diagnosis.js",
    "railway-test": "node railway_test.js",
    "health-check": "node health_check.js"
  },
  "dependencies": {
    "@supabase/supabase-js": "^2.39.0",
    "n8n": "^1.28.0",
    "express": "^4.18.2"
  },
  "engines": {
    "node": ">=20.0.0"
  },
  "keywords": [
    "telegram",
    "bot",
    "essential-oils",
    "n8n",
    "railway",
    "supabase"
  ],
  "author": "Essential Oils Bot Team",
  "license": "MIT",
  "repository": {
    "type": "git",
    "url": "https://github.com/your-username/essential-oils-bot.git"
  },
  "bugs": {
    "url": "https://github.com/your-username/essential-oils-bot/issues"
  },
  "homepage": "https://github.com/your-username/essential-oils-bot#readme"
} 